red_panda/__init__.py
red_panda/red_panda.py
red_panda/typing.py
red_panda/aws/__init__.py
red_panda/aws/athena.py
red_panda/aws/redshift.py
red_panda/aws/s3.py
red_panda/aws/templates/__init__.py
red_panda/aws/templates/redshift.py
red_panda/pandas/__init__.py
red_panda/pandas/utils.py
red_panda/utils/__init__.py
red_panda/utils/utils.py
red_panda-1.0.2.dist-info/LICENSE
red_panda-1.0.2.dist-info/METADATA
red_panda-1.0.2.dist-info/WHEEL
red_panda-1.0.2.dist-info/top_level.txt
red_panda-1.0.2.dist-info/RECORD
