Metadata-Version: 2.1
Name: red-panda
Version: 1.0.2
Summary: Data science on the cloud
Home-page: https://github.com/jucyai/red-panda
Author: Jiachen Yao
Maintainer: Jiachen Yao
License: MIT
Project-URL: Code, https://github.com/jucyai/red-panda
Project-URL: Issue tracker, https://github.com/jucyai/red-panda/issues
Platform: UNKNOWN
Classifier: Intended Audience :: Developers
Classifier: License :: OSI Approved :: MIT License
Classifier: Operating System :: OS Independent
Classifier: Programming Language :: Python
Classifier: Programming Language :: Python :: 3.6
Classifier: Programming Language :: Python :: 3.7
Classifier: Programming Language :: Python :: 3.8
Requires-Python: >=3.6
Requires-Dist: pandas (>=1.1.0)
Requires-Dist: psycopg2-binary (>=2.8.5)
Requires-Dist: boto3 (>=1.14.38)
Requires-Dist: awscli (>=1.18.115)
Requires-Dist: PyAthena (>=1.11.0)
